redist/__init__.py
redist/_version.py
redist/custom_modifier.py
redist/modifier.py
redist/plot.py
redist/style.mplstyle
redistpy-1.0.4.dist-info/METADATA
redistpy-1.0.4.dist-info/WHEEL
redistpy-1.0.4.dist-info/licenses/LICENSE
redistpy-1.0.4.dist-info/RECORD
