Metadata-Version: 2.4
Name: redistpy
Version: 1.0.4
Summary: Package for reinterpretation of particle physics results
Project-URL: Homepage, https://github.com/lorenzennio/redist
Project-URL: Documentation, https://github.com/lorenzennio/redist
Project-URL: Issue Tracker, https://github.com/lorenzennio/redist/issues
Author-email: Lorenz Gaertner <lorenz.gaertner@gmail.com>
Maintainer-email: Lorenz Gaertner <lorenz.gaertner@gmail.com>
License: MIT
License-File: LICENSE
Classifier: Development Status :: 4 - Beta
Classifier: License :: OSI Approved :: MIT License
Classifier: Programming Language :: Python :: 3 :: Only
Classifier: Programming Language :: Python :: 3.8
Classifier: Programming Language :: Python :: 3.9
Classifier: Programming Language :: Python :: 3.10
Classifier: Programming Language :: Python :: 3.11
Classifier: Programming Language :: Python :: 3.12
Classifier: Topic :: Scientific/Engineering :: Physics
Requires-Python: >=3.8
Requires-Dist: iminuit
Requires-Dist: ipykernel
Requires-Dist: jinja2
Requires-Dist: jsonschema
Requires-Dist: matplotlib
Requires-Dist: numexpr
Requires-Dist: numpy
Requires-Dist: pyhf
Requires-Dist: requests
Requires-Dist: scipy
Provides-Extra: dev
Requires-Dist: pre-commit; extra == 'dev'
Requires-Dist: pytest; extra == 'dev'
Requires-Dist: ruff>=0.11.4; extra == 'dev'
Requires-Dist: uv; extra == 'dev'
Provides-Extra: eos
Requires-Dist: dynesty==2.0.3; extra == 'eos'
Requires-Dist: eoshep>=1.0.11; extra == 'eos'
